spot2cell/__init__.py
spot2cell/logger.py
spot2cell/spot2cell.py
spot2cell/version.py
spot2cell/scripts/spots2cells.py
spot2cell-0.0.2.dist-info/LICENSE
spot2cell-0.0.2.dist-info/METADATA
spot2cell-0.0.2.dist-info/WHEEL
spot2cell-0.0.2.dist-info/entry_points.txt
spot2cell-0.0.2.dist-info/top_level.txt
spot2cell-0.0.2.dist-info/RECORD
