Metadata-Version: 2.1
Name: spot2cell
Version: 0.0.2
Summary: From a X,Y list of detected spots, assigns each spot to a cell based on a segmentation mask
Author-email: "Miguel A. Ibarra-Arellano" <c180l058j@mozmail.com>
License: AGPL-3.0-or-later
Project-URL: Repository, https://github.com/SchapiroLabor/spot2cell
Project-URL: Homepage, https://github.com/SchapiroLabor/spot2cell
Project-URL: Issues, https://github.com/SchapiroLabor/spot2cell/issues
Keywords: cell,mask,spots,FISH,Xenium
Classifier: Programming Language :: Python :: 3.9
Classifier: Programming Language :: Python :: 3.10
Classifier: Programming Language :: Python :: 3.11
Classifier: Operating System :: OS Independent
Classifier: Intended Audience :: Science/Research
Classifier: License :: OSI Approved :: GNU Affero General Public License v3
Requires-Python: >=3.9
License-File: LICENSE
Requires-Dist: numpy
Requires-Dist: tifffile
